mpl_sankey/__init__.py
mpl_sankey-0.1.0.dist-info/LICENSE
mpl_sankey-0.1.0.dist-info/METADATA
mpl_sankey-0.1.0.dist-info/WHEEL
mpl_sankey-0.1.0.dist-info/top_level.txt
mpl_sankey-0.1.0.dist-info/RECORD
