Metadata-Version: 2.1
Name: mpl-sankey
Version: 0.1.0
Summary: Sankey plots with Matplotlib
Home-page: https://github.com/toobaz/mpl_sankey
Author: Pietro Battiston
Author-email: me@pietrobattiston.it
License: GPLv3
Platform: UNKNOWN
Classifier: Programming Language :: Python :: 3
Classifier: Operating System :: OS Independent
